LICENSE
MANIFEST.in
README.md
setup.cfg
setup.py
tox.ini
fedocal_messages/__init__.py
fedocal_messages/base.py
fedocal_messages/messages.py
fedocal_messages.egg-info/PKG-INFO
fedocal_messages.egg-info/SOURCES.txt
fedocal_messages.egg-info/dependency_links.txt
fedocal_messages.egg-info/entry_points.txt
fedocal_messages.egg-info/not-zip-safe
fedocal_messages.egg-info/requires.txt
fedocal_messages.egg-info/top_level.txt
fedocal_messages/tests/__init__.py
fedocal_messages/tests/test_calendar_clear.py
fedocal_messages/tests/test_calendar_delete.py
fedocal_messages/tests/test_calendar_new.py
fedocal_messages/tests/test_calendar_update.py
fedocal_messages/tests/test_calendar_upload.py
fedocal_messages/tests/test_common.py
fedocal_messages/tests/test_meeting_delete.py
fedocal_messages/tests/test_meeting_new.py
fedocal_messages/tests/test_meeting_update.py
fedocal_messages/tests/test_object_from_topic.py
fedocal_messages/tests/test_reminder.py
fedocal_messages/tests/utils.py