Metadata-Version: 1.2
Name: fedocal-messages
Version: 1.5.0
Summary: A schema package for messages sent by fedocal
Home-page: https://pagure.io/fedocal
Maintainer: Fedora Infrastructure Team
Maintainer-email: infrastructure@lists.fedoraproject.org
License: GPLv2+
Keywords: fedora
Platform: Fedora
Platform: GNU/Linux
Classifier: License :: OSI Approved :: GNU General Public License v2 or later (GPLv2+)
Classifier: Operating System :: POSIX :: Linux
Classifier: Programming Language :: Python :: 3
Classifier: Programming Language :: Python :: 3.6
Classifier: Programming Language :: Python :: 3.7
Classifier: Programming Language :: Python :: 3.8
